LICENSE
p189sign/__init__.py
p189sign/py.typed
p189sign/util.py
p189sign-0.0.10.dist-info/LICENSE
p189sign-0.0.10.dist-info/LICENSE_zh
p189sign-0.0.10.dist-info/METADATA
p189sign-0.0.10.dist-info/WHEEL
p189sign-0.0.10.dist-info/RECORD
